<?xml version="1.0" encoding="utf-8"?>
<items>
  <item>
    <numMatiere>4</numMatiere>
    <date>17/09/2015</date>
    <heure_debut>10</heure_debut>
    <heure_fin>12</heure_fin>
    <resume_cours>Programmation C
DevC++, variables</resume_cours>
  </item>
  <item>
    <numMatiere>4</numMatiere>
    <date>02/10/2015</date>
    <heure_debut>13</heure_debut>
    <heure_fin>15</heure_fin>
    <resume_cours>TP2 : Partie observation sur les alternatives
</resume_cours>
  </item>
  <item>
    <numMatiere>4</numMatiere>
    <date>09/10/2015</date>
    <heure_debut>13</heure_debut>
    <heure_fin>15</heure_fin>
    <resume_cours>TP2 (suite) : Applications sur les alternatives
</resume_cours>
  </item>
  <item>
    <numMatiere>4</numMatiere>
    <date>16/10/2015</date>
    <heure_debut>13</heure_debut>
    <heure_fin>15</heure_fin>
    <resume_cours>TP2 (fin) : Exercices sur les alternatives doubles, suite des applications, les tableaux en c#
</resume_cours>
  </item>
  <item>
    <numMatiere>4</numMatiere>
    <date>06/11/2015</date>
    <heure_debut>13</heure_debut>
    <heure_fin>15</heure_fin>
    <resume_cours>Fin des exercices alternatives et tableaux
</resume_cours>
  </item>
  <item>
    <numMatiere>4</numMatiere>
    <date>13/11/2015</date>
    <heure_debut>13</heure_debut>
    <heure_fin>15</heure_fin>
    <resume_cours>Les fichiers séquentiels en c#. 
</resume_cours>
  </item>
  <item>
    <numMatiere>4</numMatiere>
    <date>20/11/2015</date>
    <heure_debut>13</heure_debut>
    <heure_fin>15</heure_fin>
    <resume_cours>Fichiers séquentiels en c# fin.
TD : Découverte POO Adressage IP

</resume_cours>
  </item>
  <item>
    <numMatiere>4</numMatiere>
    <date>27/11/2015</date>
    <heure_debut>13</heure_debut>
    <heure_fin>15</heure_fin>
    <resume_cours>TD : Découverte POO Adressage IP fin
</resume_cours>
  </item>
  <item>
    <numMatiere>4</numMatiere>
    <date>04/12/2015</date>
    <heure_debut>13</heure_debut>
    <heure_fin>15</heure_fin>
    <resume_cours>TD7 :Découverte sur les sous-programmes c#
</resume_cours>
  </item>
  <item>
    <numMatiere>4</numMatiere>
    <date>11/12/2015</date>
    <heure_debut>13</heure_debut>
    <heure_fin>15</heure_fin>
    <resume_cours>TD7 :Découverte sur les sous-programmes Fin
</resume_cours>
  </item>
  <item>
    <numMatiere>4</numMatiere>
    <date>08/01/2016</date>
    <heure_debut>13</heure_debut>
    <heure_fin>15</heure_fin>
    <resume_cours>TD : Découverte POO Animalerie
</resume_cours>
  </item>
  <item>
    <numMatiere>4</numMatiere>
    <date>15/01/2016</date>
    <heure_debut>13</heure_debut>
    <heure_fin>15</heure_fin>
    <resume_cours>Mise en œuvre de la POO : TP Banque
</resume_cours>
  </item>
  <item>
    <numMatiere>4</numMatiere>
    <date>29/01/2016</date>
    <heure_debut>13</heure_debut>
    <heure_fin>15</heure_fin>
    <resume_cours>Premier programme sous interface graphique (Listes)
</resume_cours>
  </item>
</items>